[
  {
    "id": "UG41070201",
    "level": 4,
    "level_name": {
      "local": "Sub-county",
      "en": "Sub-county"
    },
    "name": {
      "local": "Bisheshe Division",
      "en": "Bisheshe Division",
      "slug": "bisheshe-division"
    },
    "code": {
      "id": "UG41070201",
      "iso": null
    },
    "parent": {
      "id": "UG410702",
      "level": 3,
      "name": {
        "local": "Ibanda Municipality",
        "en": "Ibanda Municipality",
        "slug": "ibanda-municipality-ug410702"
      }
    },
    "ancestors": [
      {
        "id": "UG4",
        "level": 1,
        "name": {
          "local": "Western",
          "en": "Western",
          "slug": "western-ug4"
        }
      },
      {
        "id": "UG4107",
        "level": 2,
        "name": {
          "local": "Ibanda",
          "en": "Ibanda",
          "slug": "ibanda-ug4107"
        }
      },
      {
        "id": "UG410702",
        "level": 3,
        "name": {
          "local": "Ibanda Municipality",
          "en": "Ibanda Municipality",
          "slug": "ibanda-municipality-ug410702"
        }
      }
    ],
    "children_count": {},
    "zip_codes": [],
    "geo": {
      "lat": "-0.046",
      "lon": "30.513"
    },
    "metadata": {},
    "source": {}
  },
  {
    "id": "UG41070202",
    "level": 4,
    "level_name": {
      "local": "Sub-county",
      "en": "Sub-county"
    },
    "name": {
      "local": "Bufunda Division",
      "en": "Bufunda Division",
      "slug": "bufunda-division"
    },
    "code": {
      "id": "UG41070202",
      "iso": null
    },
    "parent": {
      "id": "UG410702",
      "level": 3,
      "name": {
        "local": "Ibanda Municipality",
        "en": "Ibanda Municipality",
        "slug": "ibanda-municipality-ug410702"
      }
    },
    "ancestors": [
      {
        "id": "UG4",
        "level": 1,
        "name": {
          "local": "Western",
          "en": "Western",
          "slug": "western-ug4"
        }
      },
      {
        "id": "UG4107",
        "level": 2,
        "name": {
          "local": "Ibanda",
          "en": "Ibanda",
          "slug": "ibanda-ug4107"
        }
      },
      {
        "id": "UG410702",
        "level": 3,
        "name": {
          "local": "Ibanda Municipality",
          "en": "Ibanda Municipality",
          "slug": "ibanda-municipality-ug410702"
        }
      }
    ],
    "children_count": {},
    "zip_codes": [],
    "geo": {
      "lat": "-0.157",
      "lon": "30.521"
    },
    "metadata": {},
    "source": {}
  },
  {
    "id": "UG41070203",
    "level": 4,
    "level_name": {
      "local": "Sub-county",
      "en": "Sub-county"
    },
    "name": {
      "local": "Kagango Division",
      "en": "Kagango Division",
      "slug": "kagango-division"
    },
    "code": {
      "id": "UG41070203",
      "iso": null
    },
    "parent": {
      "id": "UG410702",
      "level": 3,
      "name": {
        "local": "Ibanda Municipality",
        "en": "Ibanda Municipality",
        "slug": "ibanda-municipality-ug410702"
      }
    },
    "ancestors": [
      {
        "id": "UG4",
        "level": 1,
        "name": {
          "local": "Western",
          "en": "Western",
          "slug": "western-ug4"
        }
      },
      {
        "id": "UG4107",
        "level": 2,
        "name": {
          "local": "Ibanda",
          "en": "Ibanda",
          "slug": "ibanda-ug4107"
        }
      },
      {
        "id": "UG410702",
        "level": 3,
        "name": {
          "local": "Ibanda Municipality",
          "en": "Ibanda Municipality",
          "slug": "ibanda-municipality-ug410702"
        }
      }
    ],
    "children_count": {},
    "zip_codes": [],
    "geo": {
      "lat": "-0.104",
      "lon": "30.441"
    },
    "metadata": {},
    "source": {}
  }
]